gitlabber/__init__.py
gitlabber/__main__.py
gitlabber/archive.py
gitlabber/auth.py
gitlabber/cli.py
gitlabber/config.py
gitlabber/exceptions.py
gitlabber/format.py
gitlabber/git.py
gitlabber/gitlab_tree.py
gitlabber/method.py
gitlabber/naming.py
gitlabber/progress.py
gitlabber/rate_limiter.py
gitlabber/token_storage.py
gitlabber/tree_builder.py
gitlabber/url_builder.py
gitlabber-2.1.1.dist-info/licenses/LICENSE.txt
gitlabber-2.1.1.dist-info/METADATA
gitlabber-2.1.1.dist-info/WHEEL
gitlabber-2.1.1.dist-info/entry_points.txt
gitlabber-2.1.1.dist-info/top_level.txt
gitlabber-2.1.1.dist-info/RECORD
