Metadata-Version: 2.4
Name: gitlabber
Version: 2.1.1
Summary: A Gitlab clone/pull utility for backing up or cloning Gitlab groups
Author-email: Erez Mazor <erezmazor@gmail.com>
License: MIT
Project-URL: Homepage, https://github.com/ezbz/gitlabber
Project-URL: Download, https://github.com/ezbz/gitlabber/archive/main.zip
Keywords: gitlab,python,cli
Classifier: Development Status :: 4 - Beta
Classifier: Intended Audience :: Developers
Classifier: Topic :: Utilities
Classifier: License :: OSI Approved :: MIT License
Classifier: Natural Language :: English
Classifier: Operating System :: OS Independent
Classifier: Programming Language :: Python :: 3
Classifier: Programming Language :: Python :: 3.11
Classifier: Programming Language :: Python :: 3.12
Classifier: Programming Language :: Python :: 3.13
Requires-Python: >=3.11
License-File: LICENSE.txt
Requires-Dist: anytree
Requires-Dist: globre
Requires-Dist: pyyaml
Requires-Dist: pydantic>=2.7
Requires-Dist: pydantic-settings>=2.7
Requires-Dist: typer>=0.12
Requires-Dist: urllib3==2.5.0
Requires-Dist: rich
Requires-Dist: GitPython
Requires-Dist: python-gitlab
Provides-Extra: test
Requires-Dist: coverage; extra == "test"
Requires-Dist: pytest; extra == "test"
Requires-Dist: pytest-cov; extra == "test"
Requires-Dist: pytest-integration; extra == "test"
Provides-Extra: keyring
Requires-Dist: keyring>=24.0.0; extra == "keyring"
Dynamic: license-file
